tokink/__init__.py
tokink/data/ink_example.json
tokink/data/merges.txt
tokink/data/vocab.json
tokink/ink.py
tokink/processor.py
tokink/py.typed
tokink/tokinkizer.py
tokink/utils.py
tokink-0.1.1.dist-info/WHEEL
tokink-0.1.1.dist-info/METADATA
tokink-0.1.1.dist-info/RECORD
