Metadata-Version: 2.3
Name: tokink
Version: 0.1.1
Summary: A BPE tokenizer for digital ink.
Author: douglasswng
Author-email: douglasswng <douglasswng@gmail.com>
License: MIT License
Requires-Dist: matplotlib>=3.10.8
Requires-Dist: pydantic>=2.12.5
Requires-Dist: scipy>=1.17.0
Requires-Dist: tokenizers>=0.22.2
Requires-Python: >=3.12
